setup.cfg
setup.py
aph/_init_.py
aph/main.py
aph.egg-info/PKG-INFO
aph.egg-info/SOURCES.txt
aph.egg-info/dependency_links.txt
aph.egg-info/not-zip-safe
aph.egg-info/top_level.txt