Metadata-Version: 1.0
Name: aph
Version: 0.0
Summary: check nexus beeline
Home-page: UNKNOWN
Author: UNKNOWN
Author-email: alexey.pha@gmail.com
License: UNKNOWN
Platform: UNKNOWN
